{
    "image_name": "ex2-tale-of-kieu-version-1866-page01b_Page1.png",
    "status_code": 200,
    "response": {
        "data": [
            "灡秋水濕春山",
            "花慳輸赭柳慣歛撑",
            "汶堆通渃迎城",
            "色停隊没才停和的",
            "聰明本産性至",
            "坡芸詩畫豐味欹吟",
            "宮商漏堛五音",
            "芸穫咹坦胡琹没張",
            "曲茄牺侶铖章",
            "没篇薄命吏強惱人",
            "風流窒墨紅裙",
            "春撑執齒細旬及笄",
            "掩稔帳撿幔雯",
            "墻東蜂蜓接術黙埃",
            "節皮猑燕迻梭",
            "韶光尨逊也外趑册",
            "軲嫩撑羡嗔吞",
            "梗梨皋㸃汶豫羌花",
            "淸明敵節躺竺",
            "社哭掃墓噲芜蹐淸",
            "所賒奴癀燕要",
            "姉殗懴所步行猘春",
            "習燿才子佳人",
            "馭車如浴襖裙如楠"
        ],
        "id": "1a55e5f8-5608-4cc9-bf66-601690a7f2d6",
        "info": "如果我们的项目对您有帮助，希望您也能帮助我们：https://www.kandianguji.com/about_kdgj#donate",
        "message": "success"
    }
}